collective_trace/__init__.py
collective_trace/async_logger.py
collective_trace/get_group.py
collective_trace/timeout_daemon.py
collective_trace/trace_collectives.py
collective_trace-0.1.444.dist-info/licenses/LICENSE
tests/__init__.py
tests/test_barrier.py
tests/test_batch_send_recv.py
tests/test_in_cpu.py
tests/test_in_torch.py
tests/test_rs_tensor.py
collective_trace-0.1.444.dist-info/METADATA
collective_trace-0.1.444.dist-info/WHEEL
collective_trace-0.1.444.dist-info/top_level.txt
collective_trace-0.1.444.dist-info/RECORD
